devel/time_image.py
devel/time_coords.py
devel/generate_mask_model.py
devel/time_fitter.py
danish-1.0.0.dist-info/RECORD
danish-1.0.0.dist-info/WHEEL
danish-1.0.0.dist-info/top_level.txt
danish-1.0.0.dist-info/METADATA
danish-1.0.0.dist-info/licenses/LICENSE
ups/danish.table
tests/conftest.py
tests/test_factory.py
tests/.coveragerc
tests/test_fitter.py
tests/danish_test_helpers.py
tests/data/test_atm_donuts.pkl
tests/data/AuxTelTestDonuts.pkl
tests/data/test_kolm_donuts.pkl
danish/_version.py
danish/__init__.py
danish/factory.py
danish/.gitignore
danish/_danish.cpython-311-darwin.so
danish/fitter.py
danish/data/AuxTelObsc.yaml
danish/data/RubinObsc.yaml
danish/data/ComCamObsc.yaml
notebooks/rubin_vignetting_model.asdf
notebooks/Spiders.ipynb
notebooks/Danish vs Simulation.ipynb
notebooks/Vignetting Model.ipynb
notebooks/Visualize.ipynb
notebooks/Donut Viewer.ipynb
notebooks/Caustic Check.ipynb
notebooks/Danish vs Simulation AuxTel.ipynb
notebooks/Spider Shadows.ipynb
src/danish.cpp
