Metadata-Version: 2.4
Name: danish
Version: 1.0.0
Summary: Geometric donut engine
Author-email: Josh Meyers <jmeyers314@gmail.com>
License-Expression: BSD-3-Clause
Project-URL: Homepage, https://github.com/jmeyers314/danish
Classifier: Development Status :: 3 - Alpha
Classifier: Intended Audience :: Science/Research
Classifier: Programming Language :: Python :: 3
Classifier: Topic :: Scientific/Engineering :: Astronomy
Classifier: Topic :: Scientific/Engineering :: Physics
Requires-Python: >=3.10
License-File: LICENSE
Requires-Dist: pybind11>2.10
Requires-Dist: numpy
Requires-Dist: pyyaml
Requires-Dist: galsim
Requires-Dist: batoid
Requires-Dist: scipy
Dynamic: license-file
